webbed_duck/__init__.py
webbed_duck/cli.py
webbed_duck/config.py
webbed_duck/core/__init__.py
webbed_duck/core/compiler.py
webbed_duck/core/incremental.py
webbed_duck/core/interpolation.py
webbed_duck/core/local.py
webbed_duck/core/routes.py
webbed_duck/plugins/__init__.py
webbed_duck/plugins/assets.py
webbed_duck/plugins/charts.py
webbed_duck/plugins/loader.py
webbed_duck/runtime/__init__.py
webbed_duck/runtime/paths.py
webbed_duck/server/__init__.py
webbed_duck/server/analytics.py
webbed_duck/server/app.py
webbed_duck/server/auth.py
webbed_duck/server/cache.py
webbed_duck/server/csv.py
webbed_duck/server/email.py
webbed_duck/server/execution.py
webbed_duck/server/meta.py
webbed_duck/server/overlay.py
webbed_duck/server/postprocess.py
webbed_duck/server/preprocess.py
webbed_duck/server/session.py
webbed_duck/server/share.py
webbed_duck/server/vendor.py
webbed_duck/server/ui/__init__.py
webbed_duck/server/ui/charts.py
webbed_duck/server/ui/invariants.py
webbed_duck/server/ui/layout.py
webbed_duck/server/ui/pagination.py
webbed_duck/server/ui/rpc.py
webbed_duck/server/ui/utils.py
webbed_duck/server/ui/views/__init__.py
webbed_duck/server/ui/views/cards.py
webbed_duck/server/ui/views/charts.py
webbed_duck/server/ui/views/feed.py
webbed_duck/server/ui/views/table.py
webbed_duck/server/ui/widgets/__init__.py
webbed_duck/server/ui/widgets/multi_select.py
webbed_duck/server/ui/widgets/params.py
webbed_duck/static/__init__.py
webbed_duck/static/assets/wd/cards.css
webbed_duck/static/assets/wd/chart_boot.js
webbed_duck/static/assets/wd/charts.css
webbed_duck/static/assets/wd/feed.css
webbed_duck/static/assets/wd/header.js
webbed_duck/static/assets/wd/layout.css
webbed_duck/static/assets/wd/multi_select.css
webbed_duck/static/assets/wd/multi_select.js
webbed_duck/static/assets/wd/params.css
webbed_duck/static/assets/wd/params_form.js
webbed_duck/static/assets/wd/progress.js
webbed_duck/static/assets/wd/table.css
webbed_duck/static/assets/wd/table_header.js
webbed_duck-0.35.0.dist-info/licenses/LICENSE
webbed_duck-0.35.0.dist-info/METADATA
webbed_duck-0.35.0.dist-info/WHEEL
webbed_duck-0.35.0.dist-info/entry_points.txt
webbed_duck-0.35.0.dist-info/top_level.txt
webbed_duck-0.35.0.dist-info/RECORD
