Metadata-Version: 2.4
Name: webbed-duck
Version: 0.35.0
Summary: A parameterized SQL web server for DuckDB routes compiled from Markdown
Author: Isaac Moore
Requires-Python: >=3.11
License-File: LICENSE
Requires-Dist: duckdb>=0.9.2
Requires-Dist: fastapi>=0.104.1
Requires-Dist: httpx>=0.25
Requires-Dist: uvicorn>=0.23.2
Requires-Dist: pyarrow>=14.0.1
Requires-Dist: pyzipper>=0.3.6
Requires-Dist: keyring>=24.2
Requires-Dist: markdown>=3.5
Requires-Dist: tzdata; platform_system == "Windows"
Provides-Extra: test
Requires-Dist: build>=1.2; extra == "test"
Requires-Dist: hypothesis>=6.100; extra == "test"
Dynamic: license-file
